README.rst
fodselsnummer.py
setup.py
fodselsnummer.egg-info/PKG-INFO
fodselsnummer.egg-info/SOURCES.txt
fodselsnummer.egg-info/dependency_links.txt
fodselsnummer.egg-info/top_level.txt