Metadata-Version: 1.1
Name: fodselsnummer
Version: 1.5
Summary: For generating and validating of Norwegian "birth numbers" (fodselsnummer)
Home-page: https://github.com/magnuswatn/fodselsnummer
Author: Magnus Watn
Author-email: UNKNOWN
License: MIT
Keywords: fodselsnummer personnummer norway
Platform: UNKNOWN
Classifier: Development Status :: 4 - Beta
Classifier: Intended Audience :: Developers
Classifier: License :: OSI Approved :: MIT License
Classifier: Programming Language :: Python :: 2
Classifier: Programming Language :: Python :: 2.7
Classifier: Programming Language :: Python :: 3
Classifier: Programming Language :: Python :: 3.4
Classifier: Programming Language :: Python :: 3.5
Classifier: Programming Language :: Python :: 3.6
